import_mocker/__init__.py
import_mocker-0.2.0.dist-info/LICENSE
import_mocker-0.2.0.dist-info/METADATA
import_mocker-0.2.0.dist-info/WHEEL
import_mocker-0.2.0.dist-info/top_level.txt
import_mocker-0.2.0.dist-info/RECORD
