Metadata-Version: 2.1
Name: import-mocker
Version: 0.2.0
Summary: Easily import a module and mock its dependencies in an isolated way.
Home-page: https://github.com/microsoft/python-import-mocker
Author: Microsoft Corporation
Project-URL: Bug Tracker, https://github.com/microsoft/python-import-mocker/issues
Classifier: Development Status :: 3 - Alpha
Classifier: Intended Audience :: Developers
Classifier: License :: OSI Approved :: MIT License
Classifier: Programming Language :: Python :: 3.5
Classifier: Programming Language :: Python :: 3.6
Classifier: Programming Language :: Python :: 3.7
Classifier: Programming Language :: Python :: 3.8
Classifier: Programming Language :: Python :: 3.9
Classifier: Programming Language :: Python :: 3.10
Classifier: Programming Language :: Python :: 3.11
Classifier: Operating System :: OS Independent
Requires-Python: >=3.5
License-File: LICENSE
